pyrsistence/__init__.py
pyrsistence-0.0.1.dist-info/LICENSE
pyrsistence-0.0.1.dist-info/METADATA
pyrsistence-0.0.1.dist-info/WHEEL
pyrsistence-0.0.1.dist-info/top_level.txt
pyrsistence-0.0.1.dist-info/RECORD
